tls_chameleon/__init__.py
tls_chameleon/client.py
tls_chameleon/fingerprint_gallery.py
tls_chameleon/fingerprint_updater.py
tls_chameleon/http2_simulator.py
tls_chameleon/magnet.py
tls_chameleon/profiles.py
tls_chameleon/randomizer.py
tls_chameleon-2.1.0.dist-info/METADATA
tls_chameleon-2.1.0.dist-info/WHEEL
tls_chameleon-2.1.0.dist-info/top_level.txt
tls_chameleon-2.1.0.dist-info/RECORD
