Metadata-Version: 2.4
Name: tls-chameleon
Version: 2.1.0
Summary: Anti-Fingerprinting HTTP client with easy TLS fingerprint spoofing
Author: Zinzied
Keywords: tls,fingerprint,scraping,cloudflare,bypass,anti-bot,ja3
Classifier: Development Status :: 4 - Beta
Classifier: Intended Audience :: Developers
Classifier: License :: OSI Approved :: MIT License
Classifier: Programming Language :: Python :: 3
Classifier: Programming Language :: Python :: 3.8
Classifier: Programming Language :: Python :: 3.9
Classifier: Programming Language :: Python :: 3.10
Classifier: Programming Language :: Python :: 3.11
Classifier: Programming Language :: Python :: 3.12
Classifier: Topic :: Internet :: WWW/HTTP
Classifier: Topic :: Software Development :: Libraries :: Python Modules
Requires-Python: >=3.8
Requires-Dist: httpx>=0.26.0
Provides-Extra: curl
Requires-Dist: curl_cffi>=0.6.0; extra == "curl"
Provides-Extra: ai
Requires-Dist: google-generativeai; extra == "ai"
Requires-Dist: anthropic; extra == "ai"
Requires-Dist: openai; extra == "ai"
Provides-Extra: updater
Requires-Dist: httpx>=0.26.0; extra == "updater"
Provides-Extra: all
Requires-Dist: curl_cffi>=0.6.0; extra == "all"
Requires-Dist: google-generativeai; extra == "all"
Requires-Dist: anthropic; extra == "all"
Requires-Dist: openai; extra == "all"
